boto3_large_message_utils/__init__.py
boto3_large_message_utils/builder.py
boto3_large_message_utils/constants.py
boto3_large_message_utils/exceptions.py
boto3_large_message_utils/parser.py
boto3_large_message_utils/utils/__init__.py
boto3_large_message_utils/utils/compression.py
boto3_large_message_utils/utils/s3.py
boto3_large_message_utils/utils/size.py
boto3_large_message_utils-0.2.0.dist-info/LICENSE
boto3_large_message_utils-0.2.0.dist-info/METADATA
boto3_large_message_utils-0.2.0.dist-info/WHEEL
boto3_large_message_utils-0.2.0.dist-info/top_level.txt
boto3_large_message_utils-0.2.0.dist-info/RECORD
