Metadata-Version: 2.1
Name: boto3-large-message-utils
Version: 0.2.0
Summary: This library provides a way of bypassing AWS size restrictions when using services such as SQS and SNS.
Home-page: https://github.com/ajhaining/boto3_large_message_utils
Author: Andrew Haining
Author-email: haining.aj@gmail.com
License: MIT
Keywords: aws boto3 sqs sns kinesis
Platform: UNKNOWN
Requires-Dist: boto3 (>=1.11.13)
